py_cfba/__init__.py
py_cfba/core.py
py_cfba/logging.py
py_cfba/typing.py
py_cfba-0.0.1.dist-info/LICENSE
py_cfba-0.0.1.dist-info/METADATA
py_cfba-0.0.1.dist-info/WHEEL
py_cfba-0.0.1.dist-info/top_level.txt
py_cfba-0.0.1.dist-info/RECORD
